tests/__init__.py
tests/test_ciper.py
tests/test_session.py
tests/test_session_config.py
tests/backend/__init__.py
tests/backend/client/__init__.py
tests/backend/client/test_base.py
tests/backend/client/test_pickleable_session.py
tests/backend/client/memcache/__init__.py
tests/backend/client/memcache/test_pylibmc.py
tests/backend/client/memcache/test_pymemcache.py
tests/backend/client/memcache/test_pythonmemcached.py
tests/backend/client/redis/__init__.py
tests/backend/client/redis/test_redis_py.py
tests/backend/config/__init__.py
tests/backend/config/test_base.py
tests/backend/config/test_google_cloud_datastore.py
tests/backend/config/memcache/__init__.py
tests/backend/config/memcache/test_gae.py
tests/backend/config/memcache/test_pylibmc.py
tests/backend/config/memcache/test_pymemcache.py
tests/backend/config/memcache/test_pythonmemcached.py
tests/backend/config/ndb/__init__.py
tests/backend/config/ndb/test_gae.py
tests/backend/config/redis/__init__.py
tests/backend/config/redis/test_redis_py.py
tests/issues/__init__.py
tests/issues/test_issue16.py
tests/middleware/__init__.py
tests/middleware/test_pylibmc.py
tests/middleware/test_pymemcache.py
tests/middleware/test_pythonmemcached.py
tests/middleware/test_redis_py.py
vishnu/__init__.py
vishnu/cipher.py
vishnu/middleware.py
vishnu/session.py
vishnu/util.py
vishnu/backend/__init__.py
vishnu/backend/client/__init__.py
vishnu/backend/client/google_app_engine_memcache.py
vishnu/backend/client/google_app_engine_ndb.py
vishnu/backend/client/google_cloud_datastore.py
vishnu/backend/client/memcache/__init__.py
vishnu/backend/client/memcache/gae.py
vishnu/backend/client/memcache/pylibmc.py
vishnu/backend/client/memcache/pymemcache.py
vishnu/backend/client/memcache/pythonmemcached.py
vishnu/backend/client/ndb/__init__.py
vishnu/backend/client/ndb/gae.py
vishnu/backend/client/redis/__init__.py
vishnu/backend/client/redis/redis_py.py
vishnu/backend/config/__init__.py
vishnu-3.1.1.dist-info/DESCRIPTION.rst
vishnu-3.1.1.dist-info/METADATA
vishnu-3.1.1.dist-info/RECORD
vishnu-3.1.1.dist-info/WHEEL
vishnu-3.1.1.dist-info/metadata.json
vishnu-3.1.1.dist-info/top_level.txt
