Metadata-Version: 2.0
Name: vishnu
Version: 3.1.1
Summary: Sessions for the Google App Engine Python runtime
Home-page: https://github.com/anomaly/vishnu.git
Author: Anomaly Software
Author-email: support@anomaly.net.au
License: Apache 2.0
Download-URL: https://github.com/anomaly/vishnu/archive/3.1.1.tar.gz
Platform: any
Classifier: Development Status :: 5 - Production/Stable
Classifier: Environment :: Web Environment
Classifier: License :: OSI Approved
Classifier: License :: OSI Approved :: Apache Software License
Classifier: Natural Language :: English
Classifier: Intended Audience :: Developers
Classifier: Operating System :: OS Independent
Classifier: Programming Language :: Python :: 2
Classifier: Programming Language :: Python :: 2.7
Classifier: Programming Language :: Python :: 3
Classifier: Programming Language :: Python :: 3.4
Classifier: Programming Language :: Python :: 3.5
Classifier: Programming Language :: Python :: 3.6
Classifier: Topic :: Internet :: WWW/HTTP
Classifier: Topic :: Internet :: WWW/HTTP :: Session
Classifier: Topic :: Software Development :: Libraries :: Application Frameworks
Classifier: Topic :: Software Development :: Libraries :: Python Modules
Classifier: Programming Language :: Python :: Implementation :: CPython
Classifier: Programming Language :: Python :: Implementation :: PyPy
Requires-Dist: future
Requires-Dist: pycryptodome (<3.7.0,>=3.6.0)
Provides-Extra: datastore
Requires-Dist: google-cloud-datastore; extra == 'datastore'
Provides-Extra: devel
Requires-Dist: pytest; extra == 'devel'
Requires-Dist: tox; extra == 'devel'
Requires-Dist: tox-pyenv; extra == 'devel'
Provides-Extra: pylibmc
Requires-Dist: pylibmc; extra == 'pylibmc'
Provides-Extra: pymemcache
Requires-Dist: pymemcache; extra == 'pymemcache'
Provides-Extra: python-memcached
Requires-Dist: python-memcached; extra == 'python-memcached'
Provides-Extra: redis
Requires-Dist: redis; extra == 'redis'
